Metadata-Version: 2.4
Name: iflow-mcp_ast-grep_sg-mcp
Version: 0.1.0
Summary: Add your description here
Requires-Python: >=3.13
License-File: LICENSE
Requires-Dist: pydantic>=2.11.0
Requires-Dist: mcp[cli]>=1.6.0
Requires-Dist: pyyaml>=6.0.2
Provides-Extra: dev
Requires-Dist: pytest>=8.0.0; extra == "dev"
Requires-Dist: pytest-cov>=5.0.0; extra == "dev"
Requires-Dist: pytest-mock>=3.14.0; extra == "dev"
Requires-Dist: ruff>=0.7.0; extra == "dev"
Requires-Dist: mypy>=1.13.0; extra == "dev"
Requires-Dist: types-pyyaml>=6.0.12.20250809; extra == "dev"
Dynamic: license-file
